mapContentTool.py
map_content_tool-1.3.1.dist-info/METADATA
map_content_tool-1.3.1.dist-info/WHEEL
map_content_tool-1.3.1.dist-info/entry_points.txt
map_content_tool-1.3.1.dist-info/top_level.txt
map_content_tool-1.3.1.dist-info/RECORD
