Metadata-Version: 2.1
Name: map-content-tool
Version: 1.3.1
Summary: A tool to map directory contents and save output as TXT or JSON.
Home-page: https://github.com/HousamKak/map-content-tool
Author: Housam Kak
Author-email: housam.kak20@gmail.com
Classifier: Programming Language :: Python :: 3
Classifier: License :: OSI Approved :: MIT License
Classifier: Operating System :: Microsoft :: Windows
Requires-Python: >=3.6
Requires-Dist: urwid>=2.1.2
Requires-Dist: pyperclip>=1.8.2
